calendra/__init__.py
calendra/astronomy.py
calendra/core.py
calendra/create-astronomical-data.py
calendra/equinoxes.json.gz
calendra/exceptions.py
calendra/holiday.py
calendra/precomputed_astronomy.py
calendra/registry.py
calendra/registry_tools.py
calendra/ruff.toml
calendra/skyfield_astronomy.py
calendra/solar_terms.json.gz
calendra/africa/__init__.py
calendra/africa/algeria.py
calendra/africa/angola.py
calendra/africa/benin.py
calendra/africa/ivory_coast.py
calendra/africa/kenya.py
calendra/africa/madagascar.py
calendra/africa/mozambique.py
calendra/africa/nigeria.py
calendra/africa/sao_tome.py
calendra/africa/south_africa.py
calendra/africa/tunisia.py
calendra/america/__init__.py
calendra/america/argentina.py
calendra/america/barbados.py
calendra/america/brazil.py
calendra/america/canada.py
calendra/america/chile.py
calendra/america/colombia.py
calendra/america/el_salvador.py
calendra/america/mexico.py
calendra/america/panama.py
calendra/america/paraguay.py
calendra/asia/__init__.py
calendra/asia/china.py
calendra/asia/hong_kong.py
calendra/asia/israel.py
calendra/asia/japan.py
calendra/asia/kazakhstan.py
calendra/asia/malaysia.py
calendra/asia/philippines.py
calendra/asia/qatar.py
calendra/asia/singapore.py
calendra/asia/south_korea.py
calendra/asia/taiwan.py
calendra/europe/__init__.py
calendra/europe/austria.py
calendra/europe/belarus.py
calendra/europe/belgium.py
calendra/europe/bulgaria.py
calendra/europe/cayman_islands.py
calendra/europe/croatia.py
calendra/europe/cyprus.py
calendra/europe/czech_republic.py
calendra/europe/denmark.py
calendra/europe/estonia.py
calendra/europe/european_central_bank.py
calendra/europe/finland.py
calendra/europe/france.py
calendra/europe/georgia.py
calendra/europe/germany.py
calendra/europe/greece.py
calendra/europe/guernsey.py
calendra/europe/hungary.py
calendra/europe/iceland.py
calendra/europe/ireland.py
calendra/europe/italy.py
calendra/europe/latvia.py
calendra/europe/lithuania.py
calendra/europe/luxembourg.py
calendra-7.11.1.dist-info/METADATA
calendra-7.11.1.dist-info/WHEEL
calendra-7.11.1.dist-info/top_level.txt
calendra-7.11.1.dist-info/RECORD
