Metadata-Version: 2.4
Name: calendra
Version: 7.11.1
Summary: Worldwide holidays and working days helper and toolkit.
Author-email: "Jason R. Coombs" <jaraco@jaraco.com>
License-Expression: MIT
Project-URL: Source, https://github.com/jaraco/calendra
Classifier: Development Status :: 5 - Production/Stable
Classifier: Intended Audience :: Developers
Classifier: Programming Language :: Python :: 3
Classifier: Programming Language :: Python :: 3 :: Only
Requires-Python: >=3.9
Requires-Dist: python-dateutil
Requires-Dist: lunardate
Requires-Dist: backports.zoneinfo; python_version < "3.9"
Requires-Dist: tzdata; platform_system == "Windows"
Requires-Dist: convertdate
Requires-Dist: pyluach
Requires-Dist: importlib_metadata; python_version < "3.8"
Requires-Dist: more_itertools
Provides-Extra: test
Requires-Dist: pytest!=8.1.*,>=6; extra == "test"
Requires-Dist: pygments; extra == "test"
Requires-Dist: pytest-cov; extra == "test"
Requires-Dist: pytest-pep8; extra == "test"
Requires-Dist: pandas; extra == "test"
Requires-Dist: jaraco.test>=3.2.0; extra == "test"
Requires-Dist: freezegun; extra == "test"
Provides-Extra: doc
Requires-Dist: sphinx>=3.5; extra == "doc"
Requires-Dist: jaraco.packaging>=9.3; extra == "doc"
Requires-Dist: rst.linker>=1.9; extra == "doc"
Requires-Dist: furo; extra == "doc"
Requires-Dist: sphinx-lint; extra == "doc"
Provides-Extra: astronomy
Requires-Dist: skyfield; extra == "astronomy"
Requires-Dist: skyfield-data; extra == "astronomy"
Requires-Dist: tqdm; extra == "astronomy"
Provides-Extra: check
Requires-Dist: pytest-checkdocs>=2.4; extra == "check"
Requires-Dist: pytest-ruff>=0.2.1; sys_platform != "cygwin" and extra == "check"
Provides-Extra: cover
Requires-Dist: pytest-cov; extra == "cover"
Provides-Extra: enabler
Requires-Dist: pytest-enabler>=2.2; extra == "enabler"
Provides-Extra: type
Requires-Dist: pytest-mypy; extra == "type"
